{
  "book": "dibernardo-rondo",
  "pdf": "/Users/tor.inge.jossang@aftenbladet.no/Documents/Fotballbøker/Marcus A DiBernardo - The Science of Rondo_ “Progressions, Variations & Transitions”-CreateSpace Independent Publishing Platform (2014).pdf",
  "generatedAt": "2026-03-14T15:09:43.588Z",
  "totalExercisesInDataset": 19,
  "totalIllustratedExercises": 15,
  "missingIllustrations": [
    {
      "id": "rondo-air",
      "name": "Air Rondo",
      "sourceRef": "DiBernardo 2014 s.22 'Rondo Variations - Air Rondo'",
      "bookPage": 22,
      "matchedPage": 23,
      "reason": "no-illustration-found"
    },
    {
      "id": "rondo-follow-pass",
      "name": "Rondo Variation: Follow Your Pass",
      "sourceRef": "DiBernardo 2014 s.22 'Rondo Variations - Follow your pass'",
      "bookPage": 22,
      "matchedPage": 23,
      "reason": "no-illustration-found"
    },
    {
      "id": "rondo-hold-hands",
      "name": "Rondo Variation: Players Must Hold Hands in Circle",
      "sourceRef": "DiBernardo 2014 s.22 'Rondo Variations - Players must hold hands in circle'",
      "bookPage": 22,
      "matchedPage": 23,
      "reason": "no-illustration-found"
    },
    {
      "id": "rondo-two-touch-both-feet",
      "name": "Rondo Variation: Two Touch Both Feet Mandatory",
      "sourceRef": "DiBernardo 2014 s.22 'Rondo Variations - Two touch both feet mandatory'",
      "bookPage": 22,
      "matchedPage": 23,
      "reason": "no-illustration-found"
    }
  ],
  "entries": [
    {
      "id": "rondo-10v2-one-touch",
      "name": "Rondo to 10v2 One Touch",
      "sourceRef": "DiBernardo 2014 s.27 'Rondo to 10v2 One Touch'",
      "bookPage": 27,
      "matchedPage": 28,
      "page": 29,
      "fileName": "p029-rondo-10v2-one-touch-rondo-to-10v2-one-touch.webp",
      "imageUrl": "/book-illustrations/dibernardo-rondo/p029-rondo-10v2-one-touch-rondo-to-10v2-one-touch.webp",
      "cropMode": "embedded-image",
      "embeddedImagesOnPage": 1,
      "detectedBoxesOnPage": 1,
      "width": 647,
      "height": 504,
      "bytes": 15978
    },
    {
      "id": "rondo-9v4",
      "name": "9v4 Rondo",
      "sourceRef": "DiBernardo 2014 s.24 '9v4 Rondo'",
      "bookPage": 24,
      "matchedPage": 25,
      "page": 25,
      "fileName": "p025-rondo-9v4-9v4-rondo.webp",
      "imageUrl": "/book-illustrations/dibernardo-rondo/p025-rondo-9v4-9v4-rondo.webp",
      "cropMode": "embedded-image",
      "embeddedImagesOnPage": 1,
      "detectedBoxesOnPage": 1,
      "width": 664,
      "height": 424,
      "bytes": 9358
    },
    {
      "id": "rondo-breaking-lines",
      "name": "Breaking The Lines Rondo",
      "sourceRef": "DiBernardo 2014 s.9 'Breaking the Lines Rondo'",
      "bookPage": 9,
      "matchedPage": 10,
      "page": 11,
      "fileName": "p011-rondo-breaking-lines-breaking-the-lines-rondo.webp",
      "imageUrl": "/book-illustrations/dibernardo-rondo/p011-rondo-breaking-lines-breaking-the-lines-rondo.webp",
      "cropMode": "embedded-stack",
      "embeddedImagesOnPage": 2,
      "detectedBoxesOnPage": 2,
      "width": 697,
      "height": 999,
      "bytes": 33414
    },
    {
      "id": "rondo-cognitive-ball-toss",
      "name": "Cognitive Rondo: Ball Toss",
      "sourceRef": "DiBernardo 2014 s.25 'Cognitive Rondo: Ball Toss'",
      "bookPage": 25,
      "matchedPage": 26,
      "page": 26,
      "fileName": "p026-rondo-cognitive-ball-toss-cognitive-rondo-ball-toss.webp",
      "imageUrl": "/book-illustrations/dibernardo-rondo/p026-rondo-cognitive-ball-toss-cognitive-rondo-ball-toss.webp",
      "cropMode": "embedded-image",
      "embeddedImagesOnPage": 1,
      "detectedBoxesOnPage": 1,
      "width": 624,
      "height": 392,
      "bytes": 15260
    },
    {
      "id": "rondo-cognitive-no-same-color",
      "name": "Cognitive Rondo: No Same Color Passing",
      "sourceRef": "DiBernardo 2014 s.26 'Cognitive Rondo: No Same Color Passing'",
      "bookPage": 26,
      "matchedPage": 27,
      "page": 27,
      "fileName": "p027-rondo-cognitive-no-same-color-cognitive-rondo-no-same-color-passing.webp",
      "imageUrl": "/book-illustrations/dibernardo-rondo/p027-rondo-cognitive-no-same-color-cognitive-rondo-no-same-color-passing.webp",
      "cropMode": "embedded-image",
      "embeddedImagesOnPage": 1,
      "detectedBoxesOnPage": 1,
      "width": 689,
      "height": 439,
      "bytes": 18316
    },
    {
      "id": "rondo-fundamental",
      "name": "Fundamental Rondo",
      "sourceRef": "DiBernardo 2014 s.7 'Fundamental Rondo'",
      "bookPage": 7,
      "matchedPage": 8,
      "page": 9,
      "fileName": "p009-rondo-fundamental-fundamental-rondo.webp",
      "imageUrl": "/book-illustrations/dibernardo-rondo/p009-rondo-fundamental-fundamental-rondo.webp",
      "cropMode": "embedded-image",
      "embeddedImagesOnPage": 1,
      "detectedBoxesOnPage": 1,
      "width": 608,
      "height": 350,
      "bytes": 15008
    },
    {
      "id": "rondo-game-related",
      "name": "Game Related Rondo Transition",
      "sourceRef": "DiBernardo 2014 s.29 'Game Related Rondo Transition'",
      "bookPage": 29,
      "matchedPage": 30,
      "page": 31,
      "fileName": "p031-rondo-game-related-game-related-rondo-transition.webp",
      "imageUrl": "/book-illustrations/dibernardo-rondo/p031-rondo-game-related-game-related-rondo-transition.webp",
      "cropMode": "embedded-image",
      "embeddedImagesOnPage": 1,
      "detectedBoxesOnPage": 1,
      "width": 664,
      "height": 447,
      "bytes": 16542
    },
    {
      "id": "rondo-line-passing",
      "name": "Line Passing Rondo",
      "sourceRef": "DiBernardo 2014 s.16 'Line Passing Rondo'",
      "bookPage": 16,
      "matchedPage": 17,
      "page": 17,
      "fileName": "p017-rondo-line-passing-line-passing-rondo.webp",
      "imageUrl": "/book-illustrations/dibernardo-rondo/p017-rondo-line-passing-line-passing-rondo.webp",
      "cropMode": "embedded-image",
      "embeddedImagesOnPage": 1,
      "detectedBoxesOnPage": 1,
      "width": 607,
      "height": 377,
      "bytes": 14592
    },
    {
      "id": "rondo-moving",
      "name": "Moving Rondo",
      "sourceRef": "DiBernardo 2014 s.11 'Moving Rondo'",
      "bookPage": 11,
      "matchedPage": 12,
      "page": 13,
      "fileName": "p013-rondo-moving-moving-rondo.webp",
      "imageUrl": "/book-illustrations/dibernardo-rondo/p013-rondo-moving-moving-rondo.webp",
      "cropMode": "embedded-stack",
      "embeddedImagesOnPage": 2,
      "detectedBoxesOnPage": 2,
      "width": 633,
      "height": 923,
      "bytes": 27436
    },
    {
      "id": "rondo-moving-circle",
      "name": "Moving Circle Rondo",
      "sourceRef": "DiBernardo 2014 s.15 'Moving Circle Rondo'",
      "bookPage": 15,
      "matchedPage": 16,
      "page": 16,
      "fileName": "p016-rondo-moving-circle-moving-circle-rondo.webp",
      "imageUrl": "/book-illustrations/dibernardo-rondo/p016-rondo-moving-circle-moving-circle-rondo.webp",
      "cropMode": "embedded-image",
      "embeddedImagesOnPage": 1,
      "detectedBoxesOnPage": 1,
      "width": 648,
      "height": 464,
      "bytes": 13044
    },
    {
      "id": "rondo-pushup",
      "name": "Rondo Push Up Game",
      "sourceRef": "DiBernardo 2014 s.23 'Rondo Push Up Game'",
      "bookPage": 23,
      "matchedPage": 24,
      "page": 24,
      "fileName": "p024-rondo-pushup-rondo-push-up-game.webp",
      "imageUrl": "/book-illustrations/dibernardo-rondo/p024-rondo-pushup-rondo-push-up-game.webp",
      "cropMode": "embedded-image",
      "embeddedImagesOnPage": 1,
      "detectedBoxesOnPage": 1,
      "width": 664,
      "height": 377,
      "bytes": 15522
    },
    {
      "id": "rondo-sliding-player",
      "name": "Sliding Player Rondo",
      "sourceRef": "DiBernardo 2014 s.21 'Sliding Player Rondo'",
      "bookPage": 21,
      "matchedPage": 22,
      "page": 22,
      "fileName": "p022-rondo-sliding-player-sliding-player-rondo.webp",
      "imageUrl": "/book-illustrations/dibernardo-rondo/p022-rondo-sliding-player-sliding-player-rondo.webp",
      "cropMode": "embedded-image",
      "embeddedImagesOnPage": 1,
      "detectedBoxesOnPage": 1,
      "width": 624,
      "height": 419,
      "bytes": 16136
    },
    {
      "id": "rondo-to-possession",
      "name": "Rondo to Possession to Rondo",
      "sourceRef": "DiBernardo 2014 s.18 'Rondo to Possession to Rondo'",
      "bookPage": 18,
      "matchedPage": 18,
      "page": 19,
      "fileName": "p019-rondo-to-possession-rondo-to-possession-to-rondo.webp",
      "imageUrl": "/book-illustrations/dibernardo-rondo/p019-rondo-to-possession-rondo-to-possession-to-rondo.webp",
      "cropMode": "embedded-image",
      "embeddedImagesOnPage": 1,
      "detectedBoxesOnPage": 1,
      "width": 677,
      "height": 392,
      "bytes": 14322
    },
    {
      "id": "rondo-transitions",
      "name": "Rondo Transitions to Passing Patterns, Technical Training and Fitness",
      "sourceRef": "DiBernardo 2014 s.20 'Rondo Transitions To Passing Patterns, Technical Training and Fitness'",
      "bookPage": 20,
      "matchedPage": 20,
      "page": 21,
      "fileName": "p021-rondo-transitions-rondo-transitions-to-passing-patterns-technical-training-and-fitness.webp",
      "imageUrl": "/book-illustrations/dibernardo-rondo/p021-rondo-transitions-rondo-transitions-to-passing-patterns-technical-training-and-fitness.webp",
      "cropMode": "embedded-stack",
      "embeddedImagesOnPage": 2,
      "detectedBoxesOnPage": 2,
      "width": 664,
      "height": 848,
      "bytes": 30826
    },
    {
      "id": "rondo-two-team-color",
      "name": "Two Team Color Coded Rondo",
      "sourceRef": "DiBernardo 2014 s.14 'Two Team Color Coded Rondo'",
      "bookPage": 14,
      "matchedPage": 14,
      "page": 15,
      "fileName": "p015-rondo-two-team-color-two-team-color-coded-rondo.webp",
      "imageUrl": "/book-illustrations/dibernardo-rondo/p015-rondo-two-team-color-two-team-color-coded-rondo.webp",
      "cropMode": "embedded-image",
      "embeddedImagesOnPage": 1,
      "detectedBoxesOnPage": 1,
      "width": 664,
      "height": 390,
      "bytes": 14450
    }
  ]
}
